MANIFEST.in
README.md
requirements.txt
setup.cfg
setup.py
lightdo/__init__.py
lightdo/logger.py
lightdo/main.py
lightdo/parsers.py
lightdo/utils.py
lightdo.egg-info/PKG-INFO
lightdo.egg-info/SOURCES.txt
lightdo.egg-info/dependency_links.txt
lightdo.egg-info/entry_points.txt
lightdo.egg-info/requires.txt
lightdo.egg-info/top_level.txt
lightdo/data/config.json
lightdo/data/wenku/cookie.txt
lightdo/data/wenku/data.json
lightdo/mega/__init__.py
lightdo/mega/crypto.py
lightdo/mega/errors.py
lightdo/mega/mega.py
lightdo/mega/test.py