Metadata-Version: 2.1
Name: lightdo
Version: 0.0.4.4
Summary: light novel downloader
Home-page: https://github.com/arasHi87/RaitoNoberu
Author: arasHi_
Author-email: arasi27676271@gmail.com
License: MIT
Keywords: lightdo,raito,raitonoberu,light novel downloader,novel
Platform: UNKNOWN
